haptic_harness_generator/GUI.py
haptic_harness_generator/Generator.py
haptic_harness_generator/Styles.py
haptic_harness_generator/__init__.py
haptic_harness_generator/main.py
haptic_harness_generator-0.0.299.dist-info/LICENSE
haptic_harness_generator-0.0.299.dist-info/METADATA
haptic_harness_generator-0.0.299.dist-info/WHEEL
haptic_harness_generator-0.0.299.dist-info/entry_points.txt
haptic_harness_generator-0.0.299.dist-info/top_level.txt
haptic_harness_generator-0.0.299.dist-info/RECORD
