Metadata-Version: 2.1
Name: haptic_harness_generator
Version: 0.0.299
Summary: Software to easily generate parameterized tiles for haptic harnesses
Author: kaleFruit
Project-URL: Homepage, https://github.com/HaRVI-Lab/haptic-harness
Classifier: Programming Language :: Python :: 3
Classifier: License :: OSI Approved :: MIT License
Classifier: Operating System :: OS Independent
Requires-Python: >=3.8
License-File: LICENSE
Requires-Dist: numpy
Requires-Dist: pyvista>=0.43.6
Requires-Dist: ezdxf
Requires-Dist: PyQt5
Requires-Dist: pyvistaqt
